src/__init__.py
src/advanced_search.py
src/analytics.py
src/config.py
src/converter.py
src/errors.py
src/extractor.py
src/fast_extractor.py
src/history.py
src/interactive.py
src/lyrics.py
src/main.py
src/metadata.py
src/profiles.py
src/progress.py
src/updater.py
src/utils.py
src/web.py
tests/__init__.py
tests/test_converter.py
tests/test_errors.py
tests/test_extractor.py
tests/test_main.py
tests/test_metadata.py
tests/test_progress.py
tests/test_utils.py
youtube_audio_extractor-1.2.1.dist-info/licenses/LICENSE
youtube_audio_extractor-1.2.1.dist-info/METADATA
youtube_audio_extractor-1.2.1.dist-info/WHEEL
youtube_audio_extractor-1.2.1.dist-info/entry_points.txt
youtube_audio_extractor-1.2.1.dist-info/top_level.txt
youtube_audio_extractor-1.2.1.dist-info/RECORD
