Metadata-Version: 2.4
Name: youtube-audio-extractor
Version: 1.2.1
Summary: Extract audio from YouTube videos and playlists, convert to MP3 format
Home-page: https://github.com/ketchalegend/youtube-extractor
Author: KetchaLegend
Author-email: kbepa02@gmail.com
Project-URL: Bug Reports, https://github.com/ketchalegend/youtube-extractor/issues
Project-URL: Source, https://github.com/ketchalegend/youtube-extractor
Project-URL: Documentation, https://github.com/ketchalegend/youtube-extractor#readme
Project-URL: Changelog, https://github.com/ketchalegend/youtube-extractor/blob/main/CHANGELOG.md
Classifier: Development Status :: 3 - Alpha
Classifier: Intended Audience :: End Users/Desktop
Classifier: License :: OSI Approved :: MIT License
Classifier: Operating System :: OS Independent
Classifier: Programming Language :: Python :: 3
Classifier: Programming Language :: Python :: 3.8
Classifier: Programming Language :: Python :: 3.9
Classifier: Programming Language :: Python :: 3.10
Classifier: Programming Language :: Python :: 3.11
Classifier: Topic :: Multimedia :: Sound/Audio
Classifier: Topic :: Internet :: WWW/HTTP
Requires-Python: >=3.8
License-File: LICENSE
Requires-Dist: yt-dlp>=2023.7.6
Requires-Dist: ffmpeg-python>=0.2.0
Requires-Dist: mutagen>=1.47.0
Requires-Dist: click>=8.1.0
Requires-Dist: PyYAML>=6.0
Requires-Dist: requests>=2.25.0
Requires-Dist: rich>=13.0.0
Requires-Dist: Flask>=2.3.0
Requires-Dist: packaging>=23.0
Dynamic: author
Dynamic: author-email
Dynamic: classifier
Dynamic: description
Dynamic: description-content-type
Dynamic: home-page
Dynamic: license-file
Dynamic: project-url
Dynamic: requires-dist
Dynamic: requires-python
Dynamic: summary
